{
  "lastUpdated": "2025-08-21T00:00:33.531Z",
  "stats": {
    "users": {
      "count": 87257,
      "change": -0.9
    },
    "revenue": {
      "amount": 373635,
      "change": 10.1
    },
    "projects": {
      "count": 370,
      "change": 4.8
    },
    "tasks": {
      "count": 2886,
      "change": 11.8
    }
  },
  "activities": [
    {
      "type": "project",
      "title": "New user registered",
      "timestamp": "2025-08-21T00:00:33.531Z"
    },
    {
      "type": "alert",
      "title": "Task completed",
      "timestamp": "2025-08-20T00:01:22.838Z"
    },
    {
      "type": "user",
      "title": "Task completed",
      "timestamp": "2025-08-19T00:01:37.069Z"
    },
    {
      "type": "payment",
      "title": "Payment received",
      "timestamp": "2025-08-18T00:01:07.314Z"
    },
    {
      "type": "user",
      "title": "Task assigned",
      "timestamp": "2025-08-17T00:00:29.327Z"
    }
  ],
  "weeklyActivity": [
    {
      "day": "Mon",
      "value": 35
    },
    {
      "day": "Tue",
      "value": 26
    },
    {
      "day": "Wed",
      "value": 39
    },
    {
      "day": "Thu",
      "value": 83
    },
    {
      "day": "Fri",
      "value": 44
    },
    {
      "day": "Sat",
      "value": 10
    },
    {
      "day": "Sun",
      "value": 39
    }
  ],
  "performanceMetrics": [
    {
      "date": "2023-11-11",
      "value": 11
    },
    {
      "date": "2023-11-12",
      "value": 17
    },
    {
      "date": "2023-11-13",
      "value": 38
    },
    {
      "date": "2023-11-14",
      "value": 38
    },
    {
      "date": "2023-11-15",
      "value": 49
    },
    {
      "date": "2023-11-16",
      "value": 28
    },
    {
      "date": "2023-11-17",
      "value": 34
    }
  ]
}