{
  "lastUpdated": "2025-09-12T00:00:40.181Z",
  "stats": {
    "users": {
      "count": 155532,
      "change": 9.5
    },
    "revenue": {
      "amount": 539041,
      "change": -1.1
    },
    "projects": {
      "count": 375,
      "change": 3.3
    },
    "tasks": {
      "count": 3262,
      "change": 18.9
    }
  },
  "activities": [
    {
      "type": "message",
      "title": "User updated profile",
      "timestamp": "2025-09-12T00:00:40.181Z"
    },
    {
      "type": "alert",
      "title": "Project created",
      "timestamp": "2025-09-11T00:00:58.048Z"
    },
    {
      "type": "payment",
      "title": "Project created",
      "timestamp": "2025-09-10T00:00:39.649Z"
    },
    {
      "type": "alert",
      "title": "Task assigned",
      "timestamp": "2025-09-09T00:00:22.719Z"
    },
    {
      "type": "user",
      "title": "Invoice generated",
      "timestamp": "2025-09-08T00:00:39.867Z"
    }
  ],
  "weeklyActivity": [
    {
      "day": "Mon",
      "value": 10
    },
    {
      "day": "Tue",
      "value": 38
    },
    {
      "day": "Wed",
      "value": 45
    },
    {
      "day": "Thu",
      "value": 70
    },
    {
      "day": "Fri",
      "value": 19
    },
    {
      "day": "Sat",
      "value": 13
    },
    {
      "day": "Sun",
      "value": 49
    }
  ],
  "performanceMetrics": [
    {
      "date": "2023-12-03",
      "value": 17
    },
    {
      "date": "2023-12-04",
      "value": 32
    },
    {
      "date": "2023-12-05",
      "value": 28
    },
    {
      "date": "2023-12-06",
      "value": 11
    },
    {
      "date": "2023-12-07",
      "value": 20
    },
    {
      "date": "2023-12-08",
      "value": 38
    },
    {
      "date": "2023-12-09",
      "value": 21
    }
  ]
}